llama_index/storage/index_store/azurecosmosnosql/__init__.py
llama_index/storage/index_store/azurecosmosnosql/base.py
llama_index_storage_index_store_azurecosmosnosql-1.3.1.dist-info/METADATA
llama_index_storage_index_store_azurecosmosnosql-1.3.1.dist-info/WHEEL
llama_index_storage_index_store_azurecosmosnosql-1.3.1.dist-info/licenses/LICENSE
llama_index_storage_index_store_azurecosmosnosql-1.3.1.dist-info/RECORD
