Metadata-Version: 2.4
Name: llama-index-storage-index-store-azurecosmosnosql
Version: 1.3.1
Summary: llama-index storage-index-store azure cosmosdb nosql integration
Author-email: Aayush Kataria <aayushkataria3011@gmail.com>
License-Expression: MIT
License-File: LICENSE
Requires-Python: <4.0,>=3.9
Requires-Dist: azure-cosmos<5,>=4.7.0
Requires-Dist: azure-identity<2,>=1.7.1
Requires-Dist: llama-index-core<0.15,>=0.13.0
Requires-Dist: llama-index-storage-kv-store-azurecosmosnosql>=1.2.0
